huami_token/__init__.py
huami_token/__main__.py
huami_token/errors.py
huami_token/huami_token.py
huami_token/urls.py
huami_token-0.7.0.dist-info/entry_points.txt
huami_token-0.7.0.dist-info/WHEEL
huami_token-0.7.0.dist-info/METADATA
huami_token-0.7.0.dist-info/RECORD
