Metadata-Version: 2.1
Name: huami_token
Version: 0.7.0
Summary: This script retrieves the Bluetooth access token for the watch or band from Huami servers. Additionally, it downloads the AGPS data packs, cep_alm_pak.zip and cep_7days.zip.
Author-email: Kirill Snezhko <kirill.snezhko@pm.me>
Requires-Python: >=3.7
Classifier: Programming Language :: Python :: 3
Classifier: License :: OSI Approved :: MIT License
Classifier: Operating System :: OS Independent
Requires-Dist: requests == 2.25.1
Requires-Dist: types-requests == 2.25.1
Requires-Dist: pytest-pylint==0.18.0 ; extra == "test"
Requires-Dist: pytest-flake8==1.0.6 ; extra == "test"
Project-URL: Bug Tracker, https://codeberg.org/argrento/huami-token/issues
Project-URL: Homepage, https://codeberg.org/argrento/huami-token
Provides-Extra: test
